monitoring_rag-0.0.2.dist-info/licenses/LICENSE
rag_evals/__init__.py
rag_evals/evaluator.py
rag_evals/core/__init__.py
rag_evals/core/base_metric.py
rag_evals/core/dependencies.py
rag_evals/core/error_handler.py
rag_evals/core/exceptions.py
rag_evals/core/logging.py
rag_evals/core/performance.py
rag_evals/core/pipeline.py
rag_evals/core/types.py
rag_evals/llm/__init__.py
rag_evals/llm/manager.py
rag_evals/metrics/__init__.py
rag_evals/metrics/composite/__init__.py
rag_evals/metrics/composite/base_composite.py
rag_evals/metrics/composite/llm_judge.py
rag_evals/metrics/composite/rag_certainty.py
rag_evals/metrics/composite/trust_score.py
rag_evals/metrics/generation/__init__.py
rag_evals/metrics/generation/answer_correctness.py
rag_evals/metrics/generation/answer_relevance.py
rag_evals/metrics/generation/coherence.py
rag_evals/metrics/generation/completeness.py
rag_evals/metrics/generation/faithfulness.py
rag_evals/metrics/generation/helpfulness.py
rag_evals/metrics/retrieval/__init__.py
rag_evals/metrics/retrieval/context_precision.py
rag_evals/metrics/retrieval/context_recall.py
rag_evals/metrics/retrieval/context_relevance.py
rag_evals/prompts/__init__.py
rag_evals/prompts/answer_correctness.yaml
rag_evals/prompts/answer_relevancy.yaml
rag_evals/prompts/coherence.yaml
rag_evals/prompts/completeness.yaml
rag_evals/prompts/context_precision.yaml
rag_evals/prompts/context_recall.yaml
rag_evals/prompts/context_relevance.yaml
rag_evals/prompts/faithfulness.yaml
rag_evals/prompts/helpfulness.yaml
rag_evals/prompts/llm_judge.yaml
rag_evals/prompts/manager.py
rag_evals/prompts/rag_certainty.yaml
rag_evals/prompts/templates.py
rag_evals/prompts/trust_score.yaml
monitoring_rag-0.0.2.dist-info/METADATA
monitoring_rag-0.0.2.dist-info/WHEEL
monitoring_rag-0.0.2.dist-info/top_level.txt
monitoring_rag-0.0.2.dist-info/RECORD
