Metadata-Version: 2.4
Name: monitoring-rag
Version: 0.0.2
Summary: A comprehensive, framework-agnostic library for evaluating Retrieval-Augmented Generation (RAG) pipelines.
Author-email: Abhinandan Mukherjee <abhinandan.m.0401@gmail.com>
Maintainer-email: Abhinandan Mukherjee <abhinandan.m.0401@gmail.com>
License-Expression: MIT
Project-URL: Homepage, https://github.com/ragevals/rag_evals
Project-URL: Documentation, https://rag-evals.readthedocs.io
Project-URL: Repository, https://github.com/ragevals/rag_evals
Project-URL: Issues, https://github.com/ragevals/rag_evals/issues
Keywords: rag,evaluation,llm,ai,machine-learning,nlp,retrieval,generation,langchain,azure,openai
Classifier: Programming Language :: Python :: 3
Classifier: Operating System :: OS Independent
Classifier: Topic :: Scientific/Engineering :: Artificial Intelligence
Classifier: Topic :: Software Development :: Libraries :: Python Modules
Requires-Python: >=3.8
License-File: LICENSE
Requires-Dist: langchain>=0.2.0
Requires-Dist: langchain-core>=0.2.0
Requires-Dist: langchain-openai>=0.1.7
Requires-Dist: python-dotenv>=0.19.0
Requires-Dist: datasets>=2.0.0
Requires-Dist: pydantic>=2.0.0
Requires-Dist: pandas>=1.5.0
Requires-Dist: tqdm>=4.64.0
Requires-Dist: aiohttp>=3.8.0
Requires-Dist: asyncio-throttle>=1.0.0
Requires-Dist: PyYAML>=6.0
Requires-Dist: jinja2>=3.0.0
Provides-Extra: dev
Requires-Dist: pytest>=7.0.0; extra == "dev"
Requires-Dist: pytest-asyncio>=0.21.0; extra == "dev"
Requires-Dist: pytest-cov>=4.0.0; extra == "dev"
Requires-Dist: black>=22.0.0; extra == "dev"
Requires-Dist: isort>=5.10.0; extra == "dev"
Requires-Dist: mypy>=1.0.0; extra == "dev"
Requires-Dist: pre-commit>=2.20.0; extra == "dev"
Requires-Dist: flake8>=5.0.0; extra == "dev"
Requires-Dist: sphinx>=5.0.0; extra == "dev"
Requires-Dist: sphinx-rtd-theme>=1.0.0; extra == "dev"
Requires-Dist: python-dotenv>=1.0.0; extra == "dev"
Provides-Extra: docs
Requires-Dist: sphinx>=5.0.0; extra == "docs"
Requires-Dist: sphinx-rtd-theme>=1.0.0; extra == "docs"
Requires-Dist: myst-parser>=0.18.0; extra == "docs"
Provides-Extra: test
Requires-Dist: pytest>=7.0.0; extra == "test"
Requires-Dist: pytest-asyncio>=0.21.0; extra == "test"
Requires-Dist: pytest-cov>=4.0.0; extra == "test"
Requires-Dist: python-dotenv>=1.0.0; extra == "test"
Requires-Dist: respx>=0.20.0; extra == "test"
Provides-Extra: azure
Requires-Dist: azure-identity>=1.12.0; extra == "azure"
Requires-Dist: azure-keyvault-secrets>=4.6.0; extra == "azure"
Requires-Dist: azure-storage-blob>=12.14.0; extra == "azure"
Provides-Extra: providers
Requires-Dist: langchain-anthropic>=0.1.0; extra == "providers"
Requires-Dist: langchain-google-genai>=1.0.0; extra == "providers"
Requires-Dist: langchain-huggingface>=0.0.3; extra == "providers"
Provides-Extra: all
Requires-Dist: rag_evals[azure,dev,docs,providers,test]; extra == "all"
Dynamic: license-file
